main.py
hf_trending_mcp-0.1.0.dist-info/licenses/LICENSE
hf_trending_mcp-0.1.0.dist-info/METADATA
hf_trending_mcp-0.1.0.dist-info/WHEEL
hf_trending_mcp-0.1.0.dist-info/top_level.txt
hf_trending_mcp-0.1.0.dist-info/RECORD
