Metadata-Version: 2.4
Name: hf-trending-mcp
Version: 0.1.0
Summary: server that tracks trending models, datasets, and spaces on Hugging Face.
Requires-Python: >=3.13
License-File: LICENSE
Requires-Dist: httpx>=0.28.1
Requires-Dist: mcp[cli]>=1.6.0
Dynamic: license-file
